nbb/__init__.py
nbb/_version.py
nbb/api_call.py
nbb/bot_discord.py
nbb/cli.py
nbb/config.py
nbb/idfm.py
nbb/models.py
nbb/nbb_conf.toml
next_bus_bot-1.3.2.dist-info/LICENSE.txt
next_bus_bot-1.3.2.dist-info/METADATA
next_bus_bot-1.3.2.dist-info/WHEEL
next_bus_bot-1.3.2.dist-info/entry_points.txt
next_bus_bot-1.3.2.dist-info/top_level.txt
next_bus_bot-1.3.2.dist-info/RECORD
